udl2xml/__init__.py
udl2xml/cvt_class.py
udl2xml/cvt_routine.py
udl2xml/foreignkey.py
udl2xml/implementation.py
udl2xml/index.py
udl2xml/main.py
udl2xml/method.py
udl2xml/parameter.py
udl2xml/projection.py
udl2xml/property.py
udl2xml/query.py
udl2xml/split.py
udl2xml/storage.py
udl2xml/trigger.py
udl2xml/util.py
udl2xml/xdata.py
iris_udl_to_xml-0.1.dist-info/entry_points.txt
iris_udl_to_xml-0.1.dist-info/LICENSE
iris_udl_to_xml-0.1.dist-info/WHEEL
iris_udl_to_xml-0.1.dist-info/METADATA
iris_udl_to_xml-0.1.dist-info/RECORD
