Metadata-Version: 2.1
Name: iris-udl-to-xml
Version: 0.1
Summary: Converts IRIS UDL input to XML export format.
Author-email: Gertjan Klein <gklein@parvos.nl>
Requires-Python: >=3.12
Classifier: Programming Language :: Python :: 3
Classifier: License :: OSI Approved :: Apache Software License
Classifier: Operating System :: OS Independent
Classifier: Intended Audience :: Developers
Classifier: Development Status :: 4 - Beta
Requires-Dist: lxml >=5.2.2
Project-URL: Homepage, https://github.com/gertjanklein/iris-udl-to-xml
Project-URL: Issues, https://github.com/gertjanklein/iris-udl-to-xml/issues
